<annotation>
	<folder>images</folder>
	<filename>images (7).jpeg</filename>
	<path>/Users/becca085/Desktop/images/images (7).jpeg</path>
	<source>
		<database>Unknown</database>
	</source>
	<size>
		<width>300</width>
		<height>168</height>
		<depth>3</depth>
	</size>
	<segmented>0</segmented>
	<object>
		<name>emergent</name>
		<pose>Unspecified</pose>
		<truncated>0</truncated>
		<difficult>0</difficult>
		<bndbox>
			<xmin>107</xmin>
			<ymin>27</ymin>
			<xmax>160</xmax>
			<ymax>167</ymax>
		</bndbox>
	</object>
	<object>
		<name>emergent</name>
		<pose>Unspecified</pose>
		<truncated>0</truncated>
		<difficult>0</difficult>
		<bndbox>
			<xmin>213</xmin>
			<ymin>32</ymin>
			<xmax>256</xmax>
			<ymax>167</ymax>
		</bndbox>
	</object>
	<object>
		<name>emergent</name>
		<pose>Unspecified</pose>
		<truncated>0</truncated>
		<difficult>0</difficult>
		<bndbox>
			<xmin>182</xmin>
			<ymin>31</ymin>
			<xmax>214</xmax>
			<ymax>145</ymax>
		</bndbox>
	</object>
</annotation>
